{"id":"ethanol","name":"Ethanol","category":"Medical,Material","desc":"Medical alcohol used as an ingredient in the manufacture of various medicines. Drinking while on duty is not advised. Pouring on skin treats mild infections yet causes small burns.","tags":["smallitem","chem","medical","petfood2"],"priceInfo":{"outpost":{},"city":{"minAvailable":8,"multiplier":0.9},"research":{"minAvailable":10,"multiplier":0.9},"military":{"multiplier":1.1},"mine":{"multiplier":1.1},"clown":{"minAvailable":0,"maxAvailable":2},"nightclub":{"minAvailable":4},"default":{"basePrice":60,"minAvailable":6}},"deconsTo":{},"recipes":[]}