{"id":"piratebodyarmor","name":"Separatist Body Armor","category":"Equipment","desc":"A set of body armor, partially fashioned out of improvised materials by the Jovian Separatists. It's heavier than it looks.","tags":["smallitem","clothing","separatists"],"prices":{"default":480,"outpost":480.000000,"city":576.000000,"mine":432.000000,"military":624.000000,"research":480.000000,"engineering":480.000000,"medical":480.000000,"armory":480.000000},"available":{"default":0,"outpost":0,"city":2,"mine":1,"military":4,"research":1,"engineering":0,"medical":0,"armory":0},"deconsTo":{"ballisticfiber":2},"recipes":[]}