{"id":"ballistichelmet3","name":"Riot Helmet","category":"Equipment","desc":"Designed for crowd control but equally useful against alien invaders.","tags":["smallitem","helmet"],"priceInfo":{"outpost":{"sold":false,"multiplier":1.3},"city":{"minAvailable":1,"sold":false,"multiplier":1.2},"research":{"sold":false},"military":{"minAvailable":3,"multiplier":0.9},"mine":{"sold":false},"armory":{"minAvailable":3,"multiplier":0.9},"default":{"basePrice":320}},"deconsTo":{"output":{"ballisticfiber":1},"time":10.0},"recipes":[{"required":{"ballisticfiber":2},"output":1,"machine":"fabricator","time":20.0,"skills":{"weapons":30},"requiredMoney":0}]}