{"id":"mindwipe","name":"Mind Wipe","category":"Medical","desc":"Allows you to reset your talent points. Consecutive use will result in increasingly bad memory loss, returning less and less of your initial experience.","tags":["smallitem"],"priceInfo":{"outpost":{},"city":{},"research":{"maxAvailable":1,"sold":true},"military":{},"mine":{},"default":{"basePrice":860,"sold":false}},"deconsTo":{"output":{"dementonite":2,"antipsychosis":2},"time":20.0},"recipes":[{"required":{"dementonite":4,"antipsychosis":4},"output":1,"machine":"medicalfabricator","time":60.0,"skills":{"medical":50},"requiredMoney":0}]}